alignit/__init__.py
alignit/config.py
alignit/infere.py
alignit/record.py
alignit/train.py
alignit/visualize.py
alignit/models/__init__.py
alignit/models/alignnet.py
alignit/utils/__init__.py
alignit/utils/dataset.py
alignit/utils/tfs.py
alignit/utils/zhou.py
alignit-0.0.1.dist-info/licenses/LICENSE
alignit-0.0.1.dist-info/METADATA
alignit-0.0.1.dist-info/WHEEL
alignit-0.0.1.dist-info/top_level.txt
alignit-0.0.1.dist-info/RECORD
