Metadata-Version: 2.4
Name: alignit
Version: 0.0.1
Summary: Model-free real-time robot arm alignment using one or more RGB(D) cameras.
Author: Spes Robotics
Author-email: contact@spes.ai
License: Apache 2.0
Project-URL: Documentation, https://github.com/SpesRobotics/alignit
Project-URL: Source, https://github.com/SpesRobotics/alignit
Project-URL: Tracker, https://github.com/SpesRobotics/alignit/issues
Requires-Python: >=3.8
License-File: LICENSE
Requires-Dist: torch
Requires-Dist: torchvision
Requires-Dist: numpy
Requires-Dist: datasets
Requires-Dist: gradio
Requires-Dist: transforms3d
Requires-Dist: tqdm
Requires-Dist: matplotlib
Requires-Dist: mujoco
Requires-Dist: numpy
Requires-Dist: teleop[utils]
Requires-Dist: xarm-python-sdk
Requires-Dist: draccus
Requires-Dist: lerobot
Dynamic: author
Dynamic: author-email
Dynamic: description
Dynamic: description-content-type
Dynamic: license
Dynamic: license-file
Dynamic: project-url
Dynamic: requires-dist
Dynamic: requires-python
Dynamic: summary
